openpower/__init__.py
openpower/alphaess.py
openpower/amber.py
openpower-0.1.3.dist-info/LICENSE
openpower-0.1.3.dist-info/METADATA
openpower-0.1.3.dist-info/WHEEL
openpower-0.1.3.dist-info/top_level.txt
openpower-0.1.3.dist-info/RECORD
