Metadata-Version: 2.1
Name: openpower
Version: 0.1.3
Summary: Python library for monitoring and controlling solar power systems, including batteries and inverters
Home-page: https://github.com/tris10au/openpower
Author: tris10au
Classifier: Programming Language :: Python :: 3
Classifier: License :: OSI Approved :: MIT License
Classifier: Operating System :: OS Independent
License-File: LICENSE
Requires-Dist: requests
